soda/data_sources/spark_df_connection.py
soda/data_sources/spark_df_contract_data_source.py
soda/data_sources/spark_df_cursor.py
soda/data_sources/spark_df_data_source.py
soda_core_spark_df-3.5.6.dist-info/LICENSE
soda_core_spark_df-3.5.6.dist-info/METADATA
soda_core_spark_df-3.5.6.dist-info/WHEEL
soda_core_spark_df-3.5.6.dist-info/top_level.txt
soda_core_spark_df-3.5.6.dist-info/RECORD
