Metadata-Version: 2.1
Name: soda-core-spark-df
Version: 3.5.6
License-File: LICENSE
Requires-Dist: soda-core-spark==3.5.6
Requires-Dist: pyspark<4.0.0,>=3.4.0
